bin/__init__.py
metabolisHMM-2.22.data/scripts/create-genome-phylogeny
metabolisHMM-2.22.data/scripts/search-custom-markers
metabolisHMM-2.22.data/scripts/single-marker-phylogeny
metabolisHMM-2.22.data/scripts/summarize-metabolism
metabolisHMM-2.22.dist-info/METADATA
metabolisHMM-2.22.dist-info/RECORD
metabolisHMM-2.22.dist-info/WHEEL
metabolisHMM-2.22.dist-info/top_level.txt
