Metadata-Version: 2.1
Name: metabolisHMM
Version: 2.22
Summary: Constructing phylogenies and performing functional annotations with HMM markers
Home-page: https://github.com/elizabethmcd/metabolisHMM
Author: Elizabeth McDaniel
Author-email: emcdaniel@wisc.edu
License: GNU
Platform: UNKNOWN
Requires-Dist: pandas
Requires-Dist: biopython
Requires-Dist: numpy
Requires-Dist: matplotlib
Requires-Dist: seaborn
